mcp_git_ingest/__init__.py
mcp_git_ingest/main.py
mseep_mcp_git_ingest-0.1.4.dist-info/METADATA
mseep_mcp_git_ingest-0.1.4.dist-info/WHEEL
mseep_mcp_git_ingest-0.1.4.dist-info/entry_points.txt
mseep_mcp_git_ingest-0.1.4.dist-info/licenses/LICENSE
mseep_mcp_git_ingest-0.1.4.dist-info/RECORD
