Metadata-Version: 2.4
Name: mseep-mcp-git-ingest
Version: 0.1.4
Summary: MCP Git Ingest: GitHub repository analysis tools
Author-email: mseep <support@skydeck.ai>
License: MIT
License-File: LICENSE
Requires-Python: >=3.8
Requires-Dist: fastmcp
Requires-Dist: gitpython
Requires-Dist: uvicorn
